Workbook
Name Slicer_Category: #N/A

Sheet Visualization
I1: =Reporting!I21 -> Brands | J1: =Reporting!J21 -> Total Sales | K1: =Reporting!K21 -> Total Boxes | L1: =Reporting!L21 -> Total Shipment | M1: =Reporting!M21 -> Total Cost | N1: =Reporting!N21 -> Total Profit | O1: =Reporting!O21 -> Profit %
I2: =Reporting!I22 -> Alpenliebe | J2: =Reporting!J22 -> 1029490 | K2: =Reporting!K22 -> 58052 | L2: =Reporting!L22 -> 171 | M2: =Reporting!M22 -> 534577.65 | N2: =Reporting!N22 -> 494912.35 | O2: =Reporting!O22 -> 0.48073546
I3: =Reporting!I23 -> Amul | J3: =Reporting!J23 -> 3030461 | K3: =Reporting!K23 -> 210062 | L3: =Reporting!L23 -> 522 | M3: =Reporting!M23 -> 1833257.8 | N3: =Reporting!N23 -> 1197203.2 | O3: =Reporting!O23 -> 0.39505646
I4: =Reporting!I24 -> Baker's Chocolate | J4: =Reporting!J24 -> 932491 | K4: =Reporting!K24 -> 75226 | L4: =Reporting!L24 -> 173 | M4: =Reporting!M24 -> 457456.83 | N4: =Reporting!N24 -> 475034.17 | O4: =Reporting!O24 -> 0.50942494
I5: =Reporting!I25 -> Belgian | J5: =Reporting!J25 -> 979188 | K5: =Reporting!K25 -> 87237 | L5: =Reporting!L25 -> 177 | M5: =Reporting!M25 -> 20980.499 | N5: =Reporting!N25 -> 958207.5 | O5: =Reporting!O25 -> 0.97857357
I6: =Reporting!I26 -> Binge Bites | J6: =Reporting!J26 -> 938049 | K6: =Reporting!K26 -> 82174 | L6: =Reporting!L26 -> 163 | M6: =Reporting!M26 -> 677352.06 | N6: =Reporting!N26 -> 260696.94 | O6: =Reporting!O26 -> 0.27791398
I7: =Reporting!I27 -> Cadbury | J7: =Reporting!J27 -> 3855201 | K7: =Reporting!K27 -> 276802 | L7: =Reporting!L27 -> 680 | M7: =Reporting!M27 -> 659411.98 | N7: =Reporting!N27 -> 3195789 | O7: =Reporting!O27 -> 0.82895523
I8: =Reporting!I28 -> Effete | J8: =Reporting!J28 -> 1075109 | K8: =Reporting!K28 -> 59624 | L8: =Reporting!L28 -> 172 | M8: =Reporting!M28 -> 683815.73 | N8: =Reporting!N28 -> 391293.27 | O8: =Reporting!O28 -> 0.36395683
I9: =Reporting!I29 -> Galaxy | J9: =Reporting!J29 -> 990794 | K9: =Reporting!K29 -> 61790 | L9: =Reporting!L29 -> 170 | M9: =Reporting!M29 -> 310173.44 | N9: =Reporting!N29 -> 680620.56 | O9: =Reporting!O29 -> 0.68694457
I10: =Reporting!I30 -> Hershey | J10: =Reporting!J30 -> 1992571 | K10: =Reporting!K30 -> 106362 | L10: =Reporting!L30 -> 349 | M10: =Reporting!M30 -> 578099.31 | N10: =Reporting!N30 -> 1414471.7 | O10: =Reporting!O30 -> 0.70987267
I11: =Reporting!I31 -> Lindt Excellence | J11: =Reporting!J31 -> 1015994 | K11: =Reporting!K31 -> 66004 | L11: =Reporting!L31 -> 174 | M11: =Reporting!M31 -> 45925.583 | N11: =Reporting!N31 -> 970068.42 | O11: =Reporting!O31 -> 0.95479739
I12: =Reporting!I32 -> Monin | J12: =Reporting!J32 -> 1047011 | K12: =Reporting!K32 -> 45761 | L12: =Reporting!L32 -> 178 | M12: =Reporting!M32 -> 80653.763 | N12: =Reporting!N32 -> 966357.24 | O12: =Reporting!O32 -> 0.92296761
... I17: =Reporting!I37 -> Grand Total | J17: =Reporting!J37 -> 21701722 | K17: =Reporting!K37 -> 1344574 | L17: =Reporting!L37 -> 3791 | M17: =Reporting!M37 -> 6681539.4 | N17: =Reporting!N37 -> 15020183 | O17: =Reporting!O37 -> 0.69211939

Sheet Reporting
A3: Values | I3: Months | J3: Total Sales | K3: Total Cost | L3: Total Profit | P3: Years | Q3: Profit %
A4: Sum of Amount | B4: 21701722 | C4: =GETPIVOTDATA("Sum of Amount",$A$3) -> 21701722 | I4: Jan | J4: 4720863 | K4: 1555871.7 | L4: 3164991.3 | P4: 2023 | Q4: 0.69921295
A5: Sum of Boxes | B5: 1344574 | C5: =GETPIVOTDATA("Sum of Boxes",$A$3) -> 1344574 | I5: Feb | J5: 1674323 | K5: 466890.56 | L5: 1207432.4 | P5: 2024 | Q5: 0.64907257
A6: Sum of Customers | B6: 617694 | C6: =GETPIVOTDATA("Sum of Customers",$A$3) -> 617694 | I6: Mar | J6: 1702281 | K6: 516079.69 | L6: 1186201.3
A7: Total Shipment | B7: 3791 | C7: =GETPIVOTDATA("Total Shipment",$A$3) -> 3791 | I7: Apr | J7: 1575700 | K7: 479137.45 | L7: 1096562.6 | P7: =P4 -> 2023 | Q7: =GETPIVOTDATA("Profit %",$P$3,"Years",2023) -> 0.69921295
A8: Sum of Total Cost | B8: 6681539.4 | C8: =GETPIVOTDATA("Sum of Total Cost",$A$3) -> 6681539.4 | I8: May | J8: 1677242 | K8: 489444.19 | L8: 1187797.8 | P8: =P5 -> 2024 | Q8: =GETPIVOTDATA("Profit %",$P$3,"Years",2024) -> 0.64907257
A9: Sum of Total Profit | B9: 15020183 | C9: =GETPIVOTDATA("Sum of Total Profit",$A$3) -> 15020183 | I9: Jun | J9: 1360338 | K9: 433762.29 | L9: 926575.71
A10: Sum of Profit % | B10: 0.69211939 | C10: =GETPIVOTDATA("Sum of Profit %",$A$3) -> 0.69211939 | I10: Jul | J10: 1358504 | K10: 418786.39 | L10: 939717.61
I11: Aug | J11: 1569470 | K11: 548557.39 | L11: 1020912.6
I12: Sep | J12: 1275022 | K12: 326302.54 | L12: 948719.46
I13: Oct | J13: 1478897 | K13: 472613.96 | L13: 1006283
I14: Nov | J14: 1482075 | K14: 421196.34 | L14: 1060878.7
I15: Dec | J15: 1827007 | K15: 552896.89 | L15: 1274110.1
I21: Brands | J21: Total Sales | K21: Total Boxes | L21: Total Shipment | M21: Total Cost | N21: Total Profit | O21: Profit % | R21: Top 10 Sales Person | S21: Total Sales | T21: Total Profit
A22: Country | B22: Sum of Profit % | I22: Alpenliebe | J22: 1029490 | K22: 58052 | L22: 171 | M22: 534577.65 | N22: 494912.35 | O22: 0.48073546 | R22: Dennison Crosswaite | S22: 890708 | T22: 597186.41
A23: Australia | B23: 0.68431659 | C23: =A23 -> Australia | D23: =B23 -> 0.68431659 | I23: Amul | J23: 3030461 | K23: 210062 | L23: 522 | M23: 1833257.8 | N23: 1197203.2 | O23: 0.39505646 | R23: Dotty Strutley | S23: 922635 | T23: 619837.69
A24: Canada | B24: 0.68941684 | C24: =A24 -> Canada | D24: =B24 -> 0.68941684 | I24: Baker's Chocolate | J24: 932491 | K24: 75226 | L24: 173 | M24: 457456.83 | N24: 475034.17 | O24: 0.50942494 | R24: Gigi Bohling | S24: 925057 | T24: 646165.54
A25: India | B25: 0.69917076 | C25: =A25 -> India | D25: =B25 -> 0.69917076 | I25: Belgian | J25: 979188 | K25: 87237 | L25: 177 | M25: 20980.499 | N25: 958207.5 | O25: 0.97857357 | R25: Gunar Cockshoot | S25: 913325 | T25: 640549.34
A26: New Zealand | B26: 0.67625101 | C26: =A26 -> New Zealand | D26: =B26 -> 0.67625101 | I26: Binge Bites | J26: 938049 | K26: 82174 | L26: 163 | M26: 677352.06 | N26: 260696.94 | O26: 0.27791398 | R26: Jehu Rudeforth | S26: 895363 | T26: 616665.13
A27: UK | B27: 0.69853347 | C27: =A27 -> UK | D27: =B27 -> 0.69853347 | I27: Cadbury | J27: 3855201 | K27: 276802 | L27: 680 | M27: 659411.98 | N27: 3195789 | O27: 0.82895523 | R27: Karlen McCaffrey | S27: 963956 | T27: 669657.29
A28: USA | B28: 0.70597318 | C28: =A28 -> USA | D28: =B28 -> 0.70597318 | I28: Effete | J28: 1075109 | K28: 59624 | L28: 172 | M28: 683815.73 | N28: 391293.27 | O28: 0.36395683 | R28: Madelene Upcott | S28: 897554 | T28: 597610.72
I29: Galaxy | J29: 990794 | K29: 61790 | L29: 170 | M29: 310173.44 | N29: 680620.56 | O29: 0.68694457 | R29: Rafaelita Blaksland | S29: 903616 | T29: 646552.99
I30: Hershey | J30: 1992571 | K30: 106362 | L30: 349 | M30: 578099.31 | N30: 1414471.7 | O30: 0.70987267 | R30: Roddy Speechley | S30: 957047 | T30: 671941.45
I31: Lindt Excellence | J31: 1015994 | K31: 66004 | L31: 174 | M31: 45925.583 | N31: 970068.42 | O31: 0.95479739 | R31: Wilone O'Kielt | S31: 944580 | T31: 655816.7
I32: Monin | J32: 1047011 | K32: 45761 | L32: 178 | M32: 80653.763 | N32: 966357.24 | O32: 0.92296761
I33: Nestle | J33: 1969975 | K33: 77528 | L33: 345 | M33: 323182.25 | N33: 1646792.7 | O33: 0.83594601
I34: Snicker | J34: 994021 | K34: 48730 | L34: 175 | M34: 43808.27 | N34: 950212.73 | O34: 0.95592822
I35: Weikfield | J35: 902384 | K35: 50098 | L35: 167 | M35: 124112.79 | N35: 778271.21 | O35: 0.86246123
I36: Whittaker's | J36: 948983 | K36: 39124 | L36: 175 | M36: 308731.4 | N36: 640251.6 | O36: 0.67467131
I37: Grand Total | J37: 21701722 | K37: 1344574 | L37: 3791 | M37: 6681539.4 | N37: 15020183 | O37: 0.69211939

Sheet Data Transformation
A1: Sales Person | B1: Geography | C1: Product | D1: Date | E1: Amount | F1: Customers | G1: Boxes | H1: Brands | I1: Category | J1: Size | K1: Cost per Box | L1: Total Cost
A2: ='Sales Data'!A2 -> Barr Faughny | B2: ='Sales Data'!B2 -> New Zealand | C2: ='Sales Data'!C2 -> Raspberry Choco | D2: ='Sales Data'!D2 -> 44927 | E2: ='Sales Data'!E2 -> 8414 | F2: ='Sales Data'!F2 -> 276 | G2: ='Sales Data'!G2 -> 495 | H2: =VLOOKUP($C2,'Product Data'!$A$2:$E$23,COLUMNS('Product Data'!$B$2:C2),0) -> Hershey | I2: =VLOOKUP($C2,'Product Data'!$A$2:$E$23,COLUMNS('Product Data'!$B$2:D2),0) -> Bars | J2: =VLOOKUP($C2,'Product Data'!$A$2:$E$23,COLUMNS('Product Data'!$B$2:E2),0) -> Large | K2: =VLOOKUP($C2,'Product Data'!$A$2:$E$23,COLUMNS('Product Data'!$B$2:F2),0) -> 6.0983 | L2: =Table1[[#This Row],[Cost per Box]]*Table1[[#This Row],[Boxes]] -> 3018.6585
A3: ='Sales Data'!A3 -> Dennison Crosswaite | B3: ='Sales Data'!B3 -> Canada | C3: ='Sales Data'!C3 -> White Choc | D3: ='Sales Data'!D3 -> 44927 | E3: ='Sales Data'!E3 -> 532 | F3: ='Sales Data'!F3 -> 317 | G3: ='Sales Data'!G3 -> 54 | H3: =VLOOKUP($C3,'Product Data'!$A$2:$E$23,COLUMNS('Product Data'!$B$2:C3),0) -> Belgian | I3: =VLOOKUP($C3,'Product Data'!$A$2:$E$23,COLUMNS('Product Data'!$B$2:D3),0) -> Other | J3: =VLOOKUP($C3,'Product Data'!$A$2:$E$23,COLUMNS('Product Data'!$B$2:E3),0) -> Small | K3: =VLOOKUP($C3,'Product Data'!$A$2:$E$23,COLUMNS('Product Data'!$B$2:F3),0) -> 0.2405 | L3: =Table1[[#This Row],[Cost per Box]]*Table1[[#This Row],[Boxes]] -> 12.987
A4: ='Sales Data'!A4 -> Karlen McCaffrey | B4: ='Sales Data'!B4 -> USA | C4: ='Sales Data'!C4 -> 99% Dark & Pure | D4: ='Sales Data'!D4 -> 44927 | E4: ='Sales Data'!E4 -> 5376 | F4: ='Sales Data'!F4 -> 178 | G4: ='Sales Data'!G4 -> 269 | H4: =VLOOKUP($C4,'Product Data'!$A$2:$E$23,COLUMNS('Product Data'!$B$2:C4),0) -> Amul | I4: =VLOOKUP($C4,'Product Data'!$A$2:$E$23,COLUMNS('Product Data'!$B$2:D4),0) -> Bars | J4: =VLOOKUP($C4,'Product Data'!$A$2:$E$23,COLUMNS('Product Data'!$B$2:E4),0) -> Large | K4: =VLOOKUP($C4,'Product Data'!$A$2:$E$23,COLUMNS('Product Data'!$B$2:F4),0) -> 4.6592 | L4: =Table1[[#This Row],[Cost per Box]]*Table1[[#This Row],[Boxes]] -> 1253.3248
A5: ='Sales Data'!A5 -> Barr Faughny | B5: ='Sales Data'!B5 -> New Zealand | C5: ='Sales Data'!C5 -> Baker's Choco Chips | D5: ='Sales Data'!D5 -> 44927 | E5: ='Sales Data'!E5 -> 259 | F5: ='Sales Data'!F5 -> 32 | G5: ='Sales Data'!G5 -> 22 | H5: =VLOOKUP($C5,'Product Data'!$A$2:$E$23,COLUMNS('Product Data'!$B$2:C5),0) -> Baker's Chocolate | I5: =VLOOKUP($C5,'Product Data'!$A$2:$E$23,COLUMNS('Product Data'!$B$2:D5),0) -> Bars | J5: =VLOOKUP($C5,'Product Data'!$A$2:$E$23,COLUMNS('Product Data'!$B$2:E5),0) -> Small | K5: =VLOOKUP($C5,'Product Data'!$A$2:$E$23,COLUMNS('Product Data'!$B$2:F5),0) -> 6.0811 | L5: =Table1[[#This Row],[Cost per Box]]*Table1[[#This Row],[Boxes]] -> 133.7842
A6: ='Sales Data'!A6 -> Beverie Moffet | B6: ='Sales Data'!B6 -> USA | C6: ='Sales Data'!C6 -> Manuka Honey Choco | D6: ='Sales Data'!D6 -> 44927 | E6: ='Sales Data'!E6 -> 5530 | F6: ='Sales Data'!F6 -> 4 | G6: ='Sales Data'!G6 -> 179 | H6: =VLOOKUP($C6,'Product Data'!$A$2:$E$23,COLUMNS('Product Data'!$B$2:C6),0) -> Whittaker's | I6: =VLOOKUP($C6,'Product Data'!$A$2:$E$23,COLUMNS('Product Data'!$B$2:D6),0) -> Other | J6: =VLOOKUP($C6,'Product Data'!$A$2:$E$23,COLUMNS('Product Data'!$B$2:E6),0) -> Small | K6: =VLOOKUP($C6,'Product Data'!$A$2:$E$23,COLUMNS('Product Data'!$B$2:F6),0) -> 7.8911 | L6: =Table1[[#This Row],[Cost per Box]]*Table1[[#This Row],[Boxes]] -> 1412.5069
A7: ='Sales Data'!A7 -> Rafaelita Blaksland | B7: ='Sales Data'!B7 -> India | C7: ='Sales Data'!C7 -> 85% Dark Bars | D7: ='Sales Data'!D7 -> 44927 | E7: ='Sales Data'!E7 -> 2184 | F7: ='Sales Data'!F7 -> 63 | G7: ='Sales Data'!G7 -> 122 | H7: =VLOOKUP($C7,'Product Data'!$A$2:$E$23,COLUMNS('Product Data'!$B$2:C7),0) -> Lindt Excellence | I7: =VLOOKUP($C7,'Product Data'!$A$2:$E$23,COLUMNS('Product Data'!$B$2:D7),0) -> Bars | J7: =VLOOKUP($C7,'Product Data'!$A$2:$E$23,COLUMNS('Product Data'!$B$2:E7),0) -> Small | K7: =VLOOKUP($C7,'Product Data'!$A$2:$E$23,COLUMNS('Product Data'!$B$2:F7),0) -> 0.6958 | L7: =Table1[[#This Row],[Cost per Box]]*Table1[[#This Row],[Boxes]] -> 84.8876
A8: ='Sales Data'!A8 -> Oby Sorrel | B8: ='Sales Data'!B8 -> UK | C8: ='Sales Data'!C8 -> Raspberry Choco | D8: ='Sales Data'!D8 -> 44927 | E8: ='Sales Data'!E8 -> 1057 | F8: ='Sales Data'!F8 -> 295 | G8: ='Sales Data'!G8 -> 71 | H8: =VLOOKUP($C8,'Product Data'!$A$2:$E$23,COLUMNS('Product Data'!$B$2:C8),0) -> Hershey | I8: =VLOOKUP($C8,'Product Data'!$A$2:$E$23,COLUMNS('Product Data'!$B$2:D8),0) -> Bars | J8: =VLOOKUP($C8,'Product Data'!$A$2:$E$23,COLUMNS('Product Data'!$B$2:E8),0) -> Large | K8: =VLOOKUP($C8,'Product Data'!$A$2:$E$23,COLUMNS('Product Data'!$B$2:F8),0) -> 6.0983 | L8: =Table1[[#This Row],[Cost per Box]]*Table1[[#This Row],[Boxes]] -> 432.9793
A9: ='Sales Data'!A9 -> Dotty Strutley | B9: ='Sales Data'!B9 -> Australia | C9: ='Sales Data'!C9 -> Organic Choco Syrup | D9: ='Sales Data'!D9 -> 44927 | E9: ='Sales Data'!E9 -> 1036 | F9: ='Sales Data'!F9 -> 370 | G9: ='Sales Data'!G9 -> 37 | H9: =VLOOKUP($C9,'Product Data'!$A$2:$E$23,COLUMNS('Product Data'!$B$2:C9),0) -> Monin | I9: =VLOOKUP($C9,'Product Data'!$A$2:$E$23,COLUMNS('Product Data'!$B$2:D9),0) -> Other | J9: =VLOOKUP($C9,'Product Data'!$A$2:$E$23,COLUMNS('Product Data'!$B$2:E9),0) -> Small | K9: =VLOOKUP($C9,'Product Data'!$A$2:$E$23,COLUMNS('Product Data'!$B$2:F9),0) -> 1.7625 | L9: =Table1[[#This Row],[Cost per Box]]*Table1[[#This Row],[Boxes]] -> 65.2125
A10: ='Sales Data'!A10 -> Brien Boise | B10: ='Sales Data'!B10 -> Australia | C10: ='Sales Data'!C10 -> Caramel Stuffed Bars | D10: ='Sales Data'!D10 -> 44927 | E10: ='Sales Data'!E10 -> 4039 | F10: ='Sales Data'!F10 -> 536 | G10: ='Sales Data'!G10 -> 176 | H10: =VLOOKUP($C10,'Product Data'!$A$2:$E$23,COLUMNS('Product Data'!$B$2:C10),0) -> Snicker | I10: =VLOOKUP($C10,'Product Data'!$A$2:$E$23,COLUMNS('Product Data'!$B$2:D10),0) -> Bars | J10: =VLOOKUP($C10,'Product Data'!$A$2:$E$23,COLUMNS('Product Data'!$B$2:E10),0) -> Small | K10: =VLOOKUP($C10,'Product Data'!$A$2:$E$23,COLUMNS('Product Data'!$B$2:F10),0) -> 0.899 | L10: =Table1[[#This Row],[Cost per Box]]*Table1[[#This Row],[Boxes]] -> 158.224
A11: ='Sales Data'!A11 -> Curtice Advani | B11: ='Sales Data'!B11 -> New Zealand | C11: ='Sales Data'!C11 -> Milk Bars | D11: ='Sales Data'!D11 -> 44927 | E11: ='Sales Data'!E11 -> 12894 | F11: ='Sales Data'!F11 -> 115 | G11: ='Sales Data'!G11 -> 478 | H11: =VLOOKUP($C11,'Product Data'!$A$2:$E$23,COLUMNS('Product Data'!$B$2:C11),0) -> Nestle | I11: =VLOOKUP($C11,'Product Data'!$A$2:$E$23,COLUMNS('Product Data'!$B$2:D11),0) -> Bars | J11: =VLOOKUP($C11,'Product Data'!$A$2:$E$23,COLUMNS('Product Data'!$B$2:E11),0) -> Large | K11: =VLOOKUP($C11,'Product Data'!$A$2:$E$23,COLUMNS('Product Data'!$B$2:F11),0) -> 1.8652 | L11: =Table1[[#This Row],[Cost per Box]]*Table1[[#This Row],[Boxes]] -> 891.5656
A12: ='Sales Data'!A12 -> Madelene Upcott | B12: ='Sales Data'!B12 -> USA | C12: ='Sales Data'!C12 -> Milk Bars | D12: ='Sales Data'!D12 -> 44927 | E12: ='Sales Data'!E12 -> 4669 | F12: ='Sales Data'!F12 -> 121 | G12: ='Sales Data'!G12 -> 180 | H12: =VLOOKUP($C12,'Product Data'!$A$2:$E$23,COLUMNS('Product Data'!$B$2:C12),0) -> Nestle | I12: =VLOOKUP($C12,'Product Data'!$A$2:$E$23,COLUMNS('Product Data'!$B$2:D12),0) -> Bars | J12: =VLOOKUP($C12,'Product Data'!$A$2:$E$23,COLUMNS('Product Data'!$B$2:E12),0) -> Large | K12: =VLOOKUP($C12,'Product Data'!$A$2:$E$23,COLUMNS('Product Data'!$B$2:F12),0) -> 1.8652 | L12: =Table1[[#This Row],[Cost per Box]]*Table1[[#This Row],[Boxes]] -> 335.736
A13: ='Sales Data'!A13 -> Wilone O'Kielt | B13: ='Sales Data'!B13 -> New Zealand | C13: ='Sales Data'!C13 -> Organic Choco Syrup | D13: ='Sales Data'!D13 -> 44927 | E13: ='Sales Data'!E13 -> 6377 | F13: ='Sales Data'!F13 -> 184 | G13: ='Sales Data'!G13 -> 246 | H13: =VLOOKUP($C13,'Product Data'!$A$2:$E$23,COLUMNS('Product Data'!$B$2:C13),0) -> Monin | I13: =VLOOKUP($C13,'Product Data'!$A$2:$E$23,COLUMNS('Product Data'!$B$2:D13),0) -> Other | J13: =VLOOKUP($C13,'Product Data'!$A$2:$E$23,COLUMNS('Product Data'!$B$2:E13),0) -> Small | K13: =VLOOKUP($C13,'Product Data'!$A$2:$E$23,COLUMNS('Product Data'!$B$2:F13),0) -> 1.7625 | L13: =Table1[[#This Row],[Cost per Box]]*Table1[[#This Row],[Boxes]] -> 433.575
... A3792: ='Sales Data'!A3792 -> Mallorie Waber | B3792: ='Sales Data'!B3792 -> USA | C3792: ='Sales Data'!C3792 -> Spicy Special Slims | D3792: ='Sales Data'!D3792 -> 45298 | E3792: ='Sales Data'!E3792 -> 3871 | F3792: ='Sales Data'!F3792 -> 338 | G3792: ='Sales Data'!G3792 -> 431 | H3792: =VLOOKUP($C3792,'Product Data'!$A$2:$E$23,COLUMNS('Product Data'!$B$2:C3792),0) -> Alpenliebe | I3792: =VLOOKUP($C3792,'Product Data'!$A$2:$E$23,COLUMNS('Product Data'!$B$2:D3792),0) -> Bites | J3792: =VLOOKUP($C3792,'Product Data'!$A$2:$E$23,COLUMNS('Product Data'!$B$2:E3792),0) -> Large | K3792: =VLOOKUP($C3792,'Product Data'!$A$2:$E$23,COLUMNS('Product Data'!$B$2:F3792),0) -> 9.2086 | L3792: =Table1[[#This Row],[Cost per Box]]*Table1[[#This Row],[Boxes]] -> 3968.9066

Sheet Sales Data
A1: Sales Person | B1: Geography | C1: Product | D1: Date | E1: Amount | F1: Customers | G1: Boxes
A2: Barr Faughny | B2: New Zealand | C2: Raspberry Choco | D2: 44927 | E2: 8414 | F2: 276 | G2: 495
A3: Dennison Crosswaite | B3: Canada | C3: White Choc | D3: 44927 | E3: 532 | F3: 317 | G3: 54
A4: Karlen McCaffrey | B4: USA | C4: 99% Dark & Pure | D4: 44927 | E4: 5376 | F4: 178 | G4: 269
A5: Barr Faughny | B5: New Zealand | C5: Baker's Choco Chips | D5: 44927 | E5: 259 | F5: 32 | G5: 22
A6: Beverie Moffet | B6: USA | C6: Manuka Honey Choco | D6: 44927 | E6: 5530 | F6: 4 | G6: 179
A7: Rafaelita Blaksland | B7: India | C7: 85% Dark Bars | D7: 44927 | E7: 2184 | F7: 63 | G7: 122
A8: Oby Sorrel | B8: UK | C8: Raspberry Choco | D8: 44927 | E8: 1057 | F8: 295 | G8: 71
A9: Dotty Strutley | B9: Australia | C9: Organic Choco Syrup | D9: 44927 | E9: 1036 | F9: 370 | G9: 37
A10: Brien Boise | B10: Australia | C10: Caramel Stuffed Bars | D10: 44927 | E10: 4039 | F10: 536 | G10: 176
A11: Curtice Advani | B11: New Zealand | C11: Milk Bars | D11: 44927 | E11: 12894 | F11: 115 | G11: 478
A12: Madelene Upcott | B12: USA | C12: Milk Bars | D12: 44927 | E12: 4669 | F12: 121 | G12: 180
A13: Wilone O'Kielt | B13: New Zealand | C13: Organic Choco Syrup | D13: 44927 | E13: 6377 | F13: 184 | G13: 246
... A3792: Mallorie Waber | B3792: USA | C3792: Spicy Special Slims | D3792: 45298 | E3792: 3871 | F3792: 338 | G3792: 431

Sheet Product Data
A1: Product | B1: Brands | C1: Category | D1: Size | E1: Cost per Box
A2: Milk Bars | B2: Nestle | C2: Bars | D2: Large | E2: 1.8652
A3: 50% Dark Bites | B3: Cadbury | C3: Bites | D3: Large | E3: 2.8
A4: Almond Choco | B4: Amul | C4: Bars | D4: Large | E4: 13.3485
A5: Raspberry Choco | B5: Hershey | C5: Bars | D5: Large | E5: 6.0983
A6: Mint Chip Choco | B6: Cadbury | C6: Bars | D6: Large | E6: 2.2656
A7: Eclairs | B7: Cadbury | C7: Bites | D7: Large | E7: 2.8195
A8: Drinking Coco | B8: Weikfield | C8: Other | D8: Large | E8: 2.4774
A9: 99% Dark & Pure | B9: Amul | C9: Bars | D9: Large | E9: 4.6592
A10: Orange Choco | B10: Amul | C10: Bars | D10: Large | E10: 8.787
A11: Spicy Special Slims | B11: Alpenliebe | C11: Bites | D11: Large | E11: 9.2086
A12: After Eight | B12: Nestle | C12: Bites | D12: Large | E12: 6.3416
A13: Fruit & Nut Bars | B13: Cadbury | C13: Bars | D13: Large | E13: 1.5935
... A23: Peanut Butter Cubes | B23: Hershey | C23: Bites | D23: Small | E23: 4.7065
